Workbook

Sheet Cover
B4: SHOPIFY INC. (SHOP.TO)
B5: Discounted Cash Flow Valuation Model
B7: ────────────────────────────────────────────────────────────
B8: Prepared by: | C8: Aayush | TMU Economics
B9: Date: | C9: June 2026
B10: Currency: | C10: USD (millions) unless noted
B11: Data Source: | C11: Shopify 2022–2024 Annual Reports / Investor Relations
B12: Methodology: | C12: 5-Year DCF with WACC Sensitivity Analysis
B14: DISCLAIMER: This model is built for educational and portfolio purposes only. It does not constitute investment advice. Financial data sourced from public filings. All projections are the author's own estimates and assumptions.
B18: MODEL NAVIGATION
B19: Assumptions | C19: All model inputs — revenue growth, margins, WACC, terminal growth rate
B20: Income Statement | C20: Historical (2022–2024) and projected (2025–2029) P&L
B21: Cash Flow | C21: Free cash flow build from net income
B22: DCF Output | C22: Enterprise value, equity value, implied share price, sensitivity tables
B24: COLOR CODING
B25: Blue text | C25: Hardcoded inputs — numbers you can change
B26: Black text | C26: Formulas and calculations — do not edit
B27: Green text | C27: Links pulling from another tab
B30: Built as part of self-directed finance training — FMVA (CFI) + AVFM (Valuation School)

Sheet Assumptions
A1: ASSUMPTIONS — SHOPIFY INC. DCF MODEL
A3: REVENUE GROWTH ASSUMPTIONS
A4: 2025E Revenue Growth | B4: 0.27 | C4: consensus est.
A5: 2026E Revenue Growth | B5: 0.24 | C5: slight decel from '25
A6: 2027E Revenue Growth | B6: 0.21 | C6: GMV growth maturing
A7: 2028E Revenue Growth | B7: 0.18 | C7: approaching steady state
A8: 2029E Revenue Growth | B8: 0.15
C9: 10-K p.47
A10: MARGIN ASSUMPTIONS
A11: Gross Margin % | B11: 0.54 | C11: FY24 actual ~50%
A12: R&D % of Revenue | B12: 0.12 | C12: slight decline w/ scale
A13: S&M % of Revenue | B13: 0.08
A14: G&A % of Revenue | B14: 0.055 | C14: incl. stock comp
A15: D&A % of Revenue | B15: 0.04 | C15: asset-light
A16: Capex % of Revenue | B16: 0.02 | C16: low capex intensity
A17: Tax Rate | B17: 0.15 | C17: Cdn statutory
A18: Change in NWC % of Rev | B18: 0.01
A20: WACC ASSUMPTIONS
A21: Risk-Free Rate | B21: 0.035 | C21: Cdn 10yr ~3.5%
A22: Equity Risk Premium | B22: 0.055 | C22: Damodaran Jan-26
A23: Beta | B23: 0.95 | C23: 5yr monthly vs TSX
A24: Cost of Equity | B24: =B21+B23*B22 -> 0.08725 | C24: CAPM
A25: Pre-Tax Cost of Debt | B25: 0.055 | C25: credit facility
A26: Debt Weight (D/V) | B26: 0.05
A27: Equity Weight (E/V) | B27: 0.95 | C27: mkt cap dominant
A28: WACC | B28: =B27*B24+B26*B25*(1-Assumptions!B17) -> 0.085225
A29: double-check beta vs. Bloomberg before finalizing
A30: TERMINAL VALUE ASSUMPTIONS
A31: Terminal Growth Rate (g) | B31: 0.045 | C31: long-run nom. GDP
A32: Terminal Year FCF Margin | B32: 0.2 | C32: mature SaaS benchmark
A34: SHARE DATA & BALANCE SHEET ITEMS
A35: Diluted Shares Outstanding (mm) | B35: 1270 | C35: diluted, FY24 10-K
A36: Total Debt ($mm) | B36: 0 | C36: minimal debt
A37: Cash & Equivalents ($mm) | B37: 5000 | C37: per BS
A38: Net Debt ($mm) | B38: =B36-B37 -> -5000 | C38: Debt minus Cash

Sheet Income Statement
A1: INCOME STATEMENT — SHOPIFY INC. ($USD millions)
B2: 2022A | C2: 2023A | D2: 2024A | E2: 2025E | F2: 2026E | G2: 2027E | H2: 2028E | I2: 2029E
A3: REVENUE | I3: Source: Shopify IR / 10-K
A4: Total Revenue | B4: 5600 | C4: 7061 | D4: 8877 | E4: =D4*(1+Assumptions!$B$4) -> 11273.79 | F4: =E4*(1+Assumptions!$B$5) -> 13979.5 | G4: =F4*(1+Assumptions!$B$6) -> 16915.195 | H4: =G4*(1+Assumptions!$B$7) -> 19959.93 | I4: =H4*(1+Assumptions!$B$8) -> 22953.919
A5: Revenue Growth % | B5: - | C5: =(C4-B4)/B4 -> 0.26089286 | D5: =(D4-C4)/C4 -> 0.25718737 | E5: =(E4-D4)/D4 -> 0.27 | F5: =(F4-E4)/E4 -> 0.24 | G5: =(G4-F4)/F4 -> 0.21 | H5: =(H4-G4)/G4 -> 0.18 | I5: =(I4-H4)/H4 -> 0.15
A6: GROSS PROFIT
A7: Cost of Revenue | B7: 2740 | C7: 3416 | D7: 4445 | E7: =E4*(1-Assumptions!$B$11) -> 5185.9434 | F7: =F4*(1-Assumptions!$B$11) -> 6430.5698 | G7: =G4*(1-Assumptions!$B$11) -> 7780.9895 | H7: =H4*(1-Assumptions!$B$11) -> 9181.5676 | I7: =I4*(1-Assumptions!$B$11) -> 10558.803
A8: Gross Profit | B8: =B4-B7 -> 2860 | C8: =C4-C7 -> 3645 | D8: =D4-D7 -> 4432 | E8: =E4-E7 -> 6087.8466 | F8: =F4-F7 -> 7548.9298 | G8: =G4-G7 -> 9134.205 | H8: =H4-H7 -> 10778.362 | I8: =I4-I7 -> 12395.116
A9: Gross Margin % | B9: =B8/B4 -> 0.51071429 | C9: =C8/C4 -> 0.51621583 | D9: =D8/D4 -> 0.49926777 | E9: =E8/E4 -> 0.54 | F9: =F8/F4 -> 0.54 | G9: =G8/G4 -> 0.54 | H9: =H8/H4 -> 0.54 | I9: =I8/I4 -> 0.54
A10: OPERATING EXPENSES
A11: Research & Development | B11: 1382 | C11: 1776 | D11: 2068 | E11: =E4*Assumptions!$B$12 -> 1352.8548 | F11: =F4*Assumptions!$B$12 -> 1677.54 | G11: =G4*Assumptions!$B$12 -> 2029.8233 | H11: =H4*Assumptions!$B$12 -> 2395.1915 | I11: =I4*Assumptions!$B$12 -> 2754.4703
A12: Sales & Marketing | B12: 787 | C12: 952 | D12: 1149 | E12: =E4*Assumptions!$B$13 -> 901.9032 | F12: =F4*Assumptions!$B$13 -> 1118.36 | G12: =G4*Assumptions!$B$13 -> 1353.2156 | H12: =H4*Assumptions!$B$13 -> 1596.7944 | I12: =I4*Assumptions!$B$13 -> 1836.3135
A13: General & Administrative | B13: 430 | C13: 512 | D13: 592 | E13: =E4*Assumptions!$B$14 -> 620.05845 | F13: =F4*Assumptions!$B$14 -> 768.87248 | G13: =G4*Assumptions!$B$14 -> 930.3357 | H13: =H4*Assumptions!$B$14 -> 1097.7961 | I13: =I4*Assumptions!$B$14 -> 1262.4655
A14: Total Operating Expenses | B14: =SUM(B11:B13) -> 2599 | C14: =SUM(C11:C13) -> 3240 | D14: =SUM(D11:D13) -> 3809 | E14: =SUM(E11:E13) -> 2874.8164 | F14: =SUM(F11:F13) -> 3564.7724 | G14: =SUM(G11:G13) -> 4313.3746 | H14: =SUM(H11:H13) -> 5089.782 | I14: =SUM(I11:I13) -> 5853.2493
A15: OPERATING INCOME (EBIT)
A16: EBIT | B16: =B8-B14 -> 261 | C16: =C8-C14 -> 405 | D16: =D8-D14 -> 623 | E16: =E8-E14 -> 3213.0302 | F16: =F8-F14 -> 3984.1574 | G16: =G8-G14 -> 4820.8304 | H16: =H8-H14 -> 5688.5799 | I16: =I8-I14 -> 6541.8669
A17: EBIT Margin % | B17: =IFERROR(B16/B4,0) -> 0.046607143 | C17: =IFERROR(C16/C4,0) -> 0.057357315 | D17: =IFERROR(D16/D4,0) -> 0.070181368 | E17: =IFERROR(E16/E4,0) -> 0.285 | F17: =IFERROR(F16/F4,0) -> 0.285 | G17: =IFERROR(G16/G4,0) -> 0.285 | H17: =IFERROR(H16/H4,0) -> 0.285 | I17: =IFERROR(I16/I4,0) -> 0.285
A18: D&A AND EBITDA
A19: D&A | B19: 236 | C19: 297 | D19: 365 | E19: =E4*Assumptions!$B$15 -> 450.9516 | F19: =F4*Assumptions!$B$15 -> 559.17998 | G19: =G4*Assumptions!$B$15 -> 676.60778 | H19: =H4*Assumptions!$B$15 -> 798.39718 | I19: =I4*Assumptions!$B$15 -> 918.15676
A20: EBITDA | B20: =B16+B19 -> 497 | C20: =C16+C19 -> 702 | D20: =D16+D19 -> 988 | E20: =E16+E19 -> 3663.9817 | F20: =F16+F19 -> 4543.3374 | G20: =G16+G19 -> 5497.4382 | H20: =H16+H19 -> 6486.9771 | I20: =I16+I19 -> 7460.0237
A21: EBITDA Margin % | B21: =IFERROR(B20/B4,0) -> 0.08875 | C21: =IFERROR(C20/C4,0) -> 0.099419346 | D21: =IFERROR(D20/D4,0) -> 0.11129886 | E21: =IFERROR(E20/E4,0) -> 0.325 | F21: =IFERROR(F20/F4,0) -> 0.325 | G21: =IFERROR(G20/G4,0) -> 0.325 | H21: =IFERROR(H20/H4,0) -> 0.325 | I21: =IFERROR(I20/I4,0) -> 0.325
A22: NET INCOME
A23: Taxes | B23: 96 | C23: 170 | D23: 228 | E23: =MAX(E16*Assumptions!$B$17,0) -> 481.95452 | F23: =MAX(F16*Assumptions!$B$17,0) -> 597.62361 | G23: =MAX(G16*Assumptions!$B$17,0) -> 723.12457 | H23: =MAX(H16*Assumptions!$B$17,0) -> 853.28699 | I23: =MAX(I16*Assumptions!$B$17,0) -> 981.28004
A24: Net Income | B24: =B16-B23 -> 165 | C24: =C16-C23 -> 235 | D24: =D16-D23 -> 395 | E24: =E16-E23 -> 2731.0756 | F24: =F16-F23 -> 3386.5338 | G24: =G16-G23 -> 4097.7059 | H24: =H16-H23 -> 4835.2929 | I24: =I16-I23 -> 5560.5869
A25: Net Margin % | B25: =IFERROR(B24/B4,0) -> 0.029464286 | C25: =IFERROR(C24/C4,0) -> 0.033281405 | D25: =IFERROR(D24/D4,0) -> 0.044497015 | E25: =IFERROR(E24/E4,0) -> 0.24225 | F25: =IFERROR(F24/F4,0) -> 0.24225 | G25: =IFERROR(G24/G4,0) -> 0.24225 | H25: =IFERROR(H24/H4,0) -> 0.24225 | I25: =IFERROR(I24/I4,0) -> 0.24225
A26: Note: 2022-2024 actuals per Shopify 10-K filings. Projections are author estimates.

Sheet Cash Flow
A1: FREE CASH FLOW BRIDGE — SHOPIFY INC. ($USD millions)
B2: 2022A | C2: 2023A | D2: 2024A | E2: 2025E | F2: 2026E | G2: 2027E | H2: 2028E | I2: 2029E
A3: CASH FROM OPERATIONS
A4: Net Income | B4: ='Income Statement'!B24 -> 165 | C4: ='Income Statement'!C24 -> 235 | D4: ='Income Statement'!D24 -> 395 | E4: ='Income Statement'!E24 -> 2731.0756 | F4: ='Income Statement'!F24 -> 3386.5338 | G4: ='Income Statement'!G24 -> 4097.7059 | H4: ='Income Statement'!H24 -> 4835.2929 | I4: ='Income Statement'!I24 -> 5560.5869
A5: + D&A (non-cash) | B5: ='Income Statement'!B19 -> 236 | C5: ='Income Statement'!C19 -> 297 | D5: ='Income Statement'!D19 -> 365 | E5: ='Income Statement'!E19 -> 450.9516 | F5: ='Income Statement'!F19 -> 559.17998 | G5: ='Income Statement'!G19 -> 676.60778 | H5: ='Income Statement'!H19 -> 798.39718 | I5: ='Income Statement'!I19 -> 918.15676
A6: - Change in NWC | B6: =-'Income Statement'!B4*Assumptions!$B$18 -> -56 | C6: =-'Income Statement'!C4*Assumptions!$B$18 -> -70.61 | D6: =-'Income Statement'!D4*Assumptions!$B$18 -> -88.77 | E6: =-'Income Statement'!E4*Assumptions!$B$18 -> -112.7379 | F6: =-'Income Statement'!F4*Assumptions!$B$18 -> -139.795 | G6: =-'Income Statement'!G4*Assumptions!$B$18 -> -169.15195 | H6: =-'Income Statement'!H4*Assumptions!$B$18 -> -199.5993 | I6: =-'Income Statement'!I4*Assumptions!$B$18 -> -229.53919
A7: Cash from Operations | B7: =SUM(B4:B6) -> 345 | C7: =SUM(C4:C6) -> 461.39 | D7: =SUM(D4:D6) -> 671.23 | E7: =SUM(E4:E6) -> 3069.2893 | F7: =SUM(F4:F6) -> 3805.9188 | G7: =SUM(G4:G6) -> 4605.1617 | H7: =SUM(H4:H6) -> 5434.0908 | I7: =SUM(I4:I6) -> 6249.2044
A8: CAPITAL EXPENDITURES
A9: Capex | B9: -265 | C9: -312 | D9: -385 | E9: =-'Income Statement'!E4*Assumptions!$B$16 -> -225.4758 | F9: =-'Income Statement'!F4*Assumptions!$B$16 -> -279.58999 | G9: =-'Income Statement'!G4*Assumptions!$B$16 -> -338.30389 | H9: =-'Income Statement'!H4*Assumptions!$B$16 -> -399.19859 | I9: =-'Income Statement'!I4*Assumptions!$B$16 -> -459.07838
A10: FREE CASH FLOW
A11: Free Cash Flow (FCF) | B11: =B7+B9 -> 80 | C11: =C7+C9 -> 149.39 | D11: =D7+D9 -> 286.23 | E11: =E7+E9 -> 2843.8135 | F11: =F7+F9 -> 3526.3288 | G11: =G7+G9 -> 4266.8578 | H11: =H7+H9 -> 5034.8922 | I11: =I7+I9 -> 5790.1261
A12: FCF Margin % | B12: =IFERROR(B11/'Income Statement'!B4,0) -> 0.014285714 | C12: =IFERROR(C11/'Income Statement'!C4,0) -> 0.02115706 | D12: =IFERROR(D11/'Income Statement'!D4,0) -> 0.032244001 | E12: =IFERROR(E11/'Income Statement'!E4,0) -> 0.25225 | F12: =IFERROR(F11/'Income Statement'!F4,0) -> 0.25225 | G12: =IFERROR(G11/'Income Statement'!G4,0) -> 0.25225 | H12: =IFERROR(H11/'Income Statement'!H4,0) -> 0.25225 | I12: =IFERROR(I11/'Income Statement'!I4,0) -> 0.25225
A13: NWC drag increases with revenue growth — typical for high-growth SaaS

Sheet DCF Output
A1: DCF VALUATION OUTPUT — SHOPIFY INC.
A2: Projection Period | B2: 2025E | C2: 2026E | D2: 2027E | E2: 2028E | F2: 2029E
A3: DISCOUNTED CASH FLOW ANALYSIS
A4: Free Cash Flow ($mm) | B4: ='Cash Flow'!E11 -> 2843.8135 | C4: ='Cash Flow'!F11 -> 3526.3288 | D4: ='Cash Flow'!G11 -> 4266.8578 | E4: ='Cash Flow'!H11 -> 5034.8922 | F4: ='Cash Flow'!I11 -> 5790.1261
A5: Discount Period | B5: 1 | C5: 2 | D5: 3 | E5: 4 | F5: 5
A6: Discount Factor | B6: =1/(1+Assumptions!$B$28)^B5 -> 0.9214679 | C6: =1/(1+Assumptions!$B$28)^C5 -> 0.84910309 | D6: =1/(1+Assumptions!$B$28)^D5 -> 0.78242124 | E6: =1/(1+Assumptions!$B$28)^E5 -> 0.72097605 | F6: =1/(1+Assumptions!$B$28)^F5 -> 0.66435629
A7: PV of FCF ($mm) | B7: =B4*B6 -> 2620.4829 | C7: =C4*C6 -> 2994.2167 | D7: =D4*D6 -> 3338.4802 | E7: =E4*E6 -> 3630.0367 | F7: =F4*F6 -> 3846.7067
A8: sanity check: TV should be ~65-75% of EV for high-growth co.
A9: ENTERPRISE VALUE BRIDGE
A10: Sum of PV of FCFs ($mm) | B10: =SUM(B7:F7) -> 16429.923
A11: Terminal Value ($mm) | B11: =F4*(1+Assumptions!$B$31)/(Assumptions!$B$28-Assumptions!$B$31) -> 150420.93
A12: PV of Terminal Value ($mm) | B12: =B11/(1+Assumptions!$B$28)^5 -> 99933.088
A13: Enterprise Value ($mm) | B13: =B10+B12 -> 116363.01
A14: Less: Net Debt ($mm) | B14: =Assumptions!$B$38 -> -5000
A15: Equity Value ($mm) | B15: =B13-B14 -> 121363.01
A16: Diluted Shares Outstanding (mm) | B16: =Assumptions!$B$35 -> 1270
A17: Implied Share Price (USD) | B17: =B15/B16 -> 95.561426
A19: TV as % of EV: | B19: =B12/B13 -> 0.85880459 | C19: ← high = model sensitive to terminal assumptions
A20: SENSITIVITY ANALYSIS — IMPLIED SHARE PRICE (USD)
A21: WACC \ Terminal Growth Rate | B21: 0.02 | C21: 0.025 | D21: 0.03 | E21: 0.035 | F21: 0.04
A22: 0.08 | B22: =(SUMPRODUCT('DCF Output'!B4:F4,1/(1+0.08)^{1,2,3,4,5})+F4*(1+0.02)/(0.08-0.02)/(1+0.08)^5-Assumptions!$B$38)/Assumptions!$B$35 -> 69.823866 | C22: =(SUMPRODUCT('DCF Output'!B4:F4,1/(1+0.08)^{1,2,3,4,5})+F4*(1+0.025)/(0.08-0.025)/(1+0.08)^5-Assumptions!$B$38)/Assumptions!$B$35 -> 74.901312 | D22: =(SUMPRODUCT('DCF Output'!B4:F4,1/(1+0.08)^{1,2,3,4,5})+F4*(1+0.03)/(0.08-0.03)/(1+0.08)^5-Assumptions!$B$38)/Assumptions!$B$35 -> 80.994248 | E22: =(SUMPRODUCT('DCF Output'!B4:F4,1/(1+0.08)^{1,2,3,4,5})+F4*(1+0.035)/(0.08-0.035)/(1+0.08)^5-Assumptions!$B$38)/Assumptions!$B$35 -> 88.441169 | F22: =(SUMPRODUCT('DCF Output'!B4:F4,1/(1+0.08)^{1,2,3,4,5})+F4*(1+0.04)/(0.08-0.04)/(1+0.08)^5-Assumptions!$B$38)/Assumptions!$B$35 -> 97.749821
A23: 0.09 | B23: =(SUMPRODUCT('DCF Output'!B4:F4,1/(1+0.09)^{1,2,3,4,5})+F4*(1+0.02)/(0.09-0.02)/(1+0.09)^5-Assumptions!$B$38)/Assumptions!$B$35 -> 59.871533 | C23: =(SUMPRODUCT('DCF Output'!B4:F4,1/(1+0.09)^{1,2,3,4,5})+F4*(1+0.025)/(0.09-0.025)/(1+0.09)^5-Assumptions!$B$38)/Assumptions!$B$35 -> 63.420785 | D23: =(SUMPRODUCT('DCF Output'!B4:F4,1/(1+0.09)^{1,2,3,4,5})+F4*(1+0.03)/(0.09-0.03)/(1+0.09)^5-Assumptions!$B$38)/Assumptions!$B$35 -> 67.56158 | E23: =(SUMPRODUCT('DCF Output'!B4:F4,1/(1+0.09)^{1,2,3,4,5})+F4*(1+0.035)/(0.09-0.035)/(1+0.09)^5-Assumptions!$B$38)/Assumptions!$B$35 -> 72.455246 | F23: =(SUMPRODUCT('DCF Output'!B4:F4,1/(1+0.09)^{1,2,3,4,5})+F4*(1+0.04)/(0.09-0.04)/(1+0.09)^5-Assumptions!$B$38)/Assumptions!$B$35 -> 78.327646
A24: 0.1 | B24: =(SUMPRODUCT('DCF Output'!B4:F4,1/(1+0.1)^{1,2,3,4,5})+F4*(1+0.02)/(0.1-0.02)/(1+0.1)^5-Assumptions!$B$38)/Assumptions!$B$35 -> 52.423964 | C24: =(SUMPRODUCT('DCF Output'!B4:F4,1/(1+0.1)^{1,2,3,4,5})+F4*(1+0.025)/(0.1-0.025)/(1+0.1)^5-Assumptions!$B$38)/Assumptions!$B$35 -> 55.018934 | D24: =(SUMPRODUCT('DCF Output'!B4:F4,1/(1+0.1)^{1,2,3,4,5})+F4*(1+0.03)/(0.1-0.03)/(1+0.1)^5-Assumptions!$B$38)/Assumptions!$B$35 -> 57.984613 | E24: =(SUMPRODUCT('DCF Output'!B4:F4,1/(1+0.1)^{1,2,3,4,5})+F4*(1+0.035)/(0.1-0.035)/(1+0.1)^5-Assumptions!$B$38)/Assumptions!$B$35 -> 61.406552 | F24: =(SUMPRODUCT('DCF Output'!B4:F4,1/(1+0.1)^{1,2,3,4,5})+F4*(1+0.04)/(0.1-0.04)/(1+0.1)^5-Assumptions!$B$38)/Assumptions!$B$35 -> 65.398813
A25: 0.11 | B25: =(SUMPRODUCT('DCF Output'!B4:F4,1/(1+0.11)^{1,2,3,4,5})+F4*(1+0.02)/(0.11-0.02)/(1+0.11)^5-Assumptions!$B$38)/Assumptions!$B$35 -> 46.645553 | C25: =(SUMPRODUCT('DCF Output'!B4:F4,1/(1+0.11)^{1,2,3,4,5})+F4*(1+0.025)/(0.11-0.025)/(1+0.11)^5-Assumptions!$B$38)/Assumptions!$B$35 -> 48.608466 | D25: =(SUMPRODUCT('DCF Output'!B4:F4,1/(1+0.11)^{1,2,3,4,5})+F4*(1+0.03)/(0.11-0.03)/(1+0.11)^5-Assumptions!$B$38)/Assumptions!$B$35 -> 50.816743 | E25: =(SUMPRODUCT('DCF Output'!B4:F4,1/(1+0.11)^{1,2,3,4,5})+F4*(1+0.035)/(0.11-0.035)/(1+0.11)^5-Assumptions!$B$38)/Assumptions!$B$35 -> 53.319456 | F25: =(SUMPRODUCT('DCF Output'!B4:F4,1/(1+0.11)^{1,2,3,4,5})+F4*(1+0.04)/(0.11-0.04)/(1+0.11)^5-Assumptions!$B$38)/Assumptions!$B$35 -> 56.1797
A26: 0.12 | B26: =(SUMPRODUCT('DCF Output'!B4:F4,1/(1+0.12)^{1,2,3,4,5})+F4*(1+0.02)/(0.12-0.02)/(1+0.12)^5-Assumptions!$B$38)/Assumptions!$B$35 -> 42.034972 | C26: =(SUMPRODUCT('DCF Output'!B4:F4,1/(1+0.12)^{1,2,3,4,5})+F4*(1+0.025)/(0.12-0.025)/(1+0.12)^5-Assumptions!$B$38)/Assumptions!$B$35 -> 43.559933 | D26: =(SUMPRODUCT('DCF Output'!B4:F4,1/(1+0.12)^{1,2,3,4,5})+F4*(1+0.03)/(0.12-0.03)/(1+0.12)^5-Assumptions!$B$38)/Assumptions!$B$35 -> 45.254334 | E26: =(SUMPRODUCT('DCF Output'!B4:F4,1/(1+0.12)^{1,2,3,4,5})+F4*(1+0.035)/(0.12-0.035)/(1+0.12)^5-Assumptions!$B$38)/Assumptions!$B$35 -> 47.148075 | F26: =(SUMPRODUCT('DCF Output'!B4:F4,1/(1+0.12)^{1,2,3,4,5})+F4*(1+0.04)/(0.12-0.04)/(1+0.12)^5-Assumptions!$B$38)/Assumptions!$B$35 -> 49.278535
A28: Note: Yellow cell = base case (WACC 10.0%, g 3.0%). All values in USD per share.
